kafkaesque/__init__.py
kafkaesque/consumer.py
kafkaesque-1.0.dist-info/DESCRIPTION.rst
kafkaesque-1.0.dist-info/METADATA
kafkaesque-1.0.dist-info/RECORD
kafkaesque-1.0.dist-info/WHEEL
kafkaesque-1.0.dist-info/metadata.json
kafkaesque-1.0.dist-info/top_level.txt
