Metadata-Version: 2.0
Name: kafkaesque
Version: 1.0
Summary: an easy to use kafka consumer that extends kafka-python, but follows the style of the flask server
Home-page: https://github.com/sankalpjonn/kafkaesque
Author: Sankalp Jonna
Author-email: sankalpjonna@gmail.com
License: MIT
Keywords: kafka,consumer,kafkaesque,flask,simple,consumer,flask style,decorator
Platform: UNKNOWN
Requires-Dist: kafka-python
